smileargs/SmileArgs.py
smileargs/__init__.py
SmileArgs-1.1.2.dist-info/LICENSE.txt
SmileArgs-1.1.2.dist-info/METADATA
SmileArgs-1.1.2.dist-info/WHEEL
SmileArgs-1.1.2.dist-info/top_level.txt
SmileArgs-1.1.2.dist-info/RECORD
