Metadata-Version: 2.1
Name: SmileArgs
Version: 1.1.2
Summary: It is a modern args catching with python3 and OOP structure and implementation.
Home-page: https://github.com/sitthykun/smileargs
Author: Sitthykun LY
Author-email: ly.sitthykun@gmail.com
License: MIT License
Keywords: argument,args,cli controller
Platform: All
Classifier: Programming Language :: Python :: 3.8
Classifier: Programming Language :: Python :: 3.9
Classifier: Programming Language :: Python :: 3.10
Classifier: Programming Language :: Python :: 3.11
Classifier: Programming Language :: Python :: 3.12
Classifier: License :: OSI Approved :: MIT License
Classifier: Operating System :: OS Independent
Requires-Python: >=3.8
License-File: LICENSE.txt
